README.rst
fastdupes.py
setup.cfg
setup.py
fastdupes.egg-info/PKG-INFO
fastdupes.egg-info/SOURCES.txt
fastdupes.egg-info/dependency_links.txt
fastdupes.egg-info/entry_points.txt
fastdupes.egg-info/top_level.txt