Metadata-Version: 1.0
Name: fastdupes
Version: 0.3.6
Summary: High-efficiency tool for finding sets of duplicate files
Home-page: https://github.com/ssokolow/fastdupes/
Author: Stephan Sokolow
Author-email: http://www.ssokolow.com/ContactMe
License: UNKNOWN
Platform: UNKNOWN
